[{"name": "Aalto", "id": "12", "element": "Aero", "weaponType": "Pistols"}, {"name": "Aemeath", "id": "53", "element": "Fusion", "weaponType": "Sword"}, {"name": "Augusta", "id": "51", "element": "Electro", "weaponType": "Broadblade"}, {"name": "Baizhi", "id": "6", "element": "Glacio", "weaponType": "Rectifier"}, {"name": "Brant", "id": "44", "element": "Fusion", "weaponType": "Sword"}, {"name": "Buling", "id": "58", "element": "Electro", "weaponType": "Rectifier"}, {"name": "Calcharo", "id": "18", "element": "Electro", "weaponType": "Broadblade"}, {"name": "Camellya", "id": "29", "element": "Havoc", "weaponType": "Sword"}, {"name": "Cantarella", "id": "34", "element": "Havoc", "weaponType": "Rectifier"}, {"name": "Carlotta", "id": "32", "element": "Glacio", "weaponType": "Pistols"}, {"name": "Cartethyia", "id": "40", "element": "Aero", "weaponType": "Sword"}, {"name": "Changli", "id": "26", "element": "Fusion", "weaponType": "Sword"}, {"name": "Chisa", "id": "57", "element": "Havoc", "weaponType": "Broadblade"}, {"name": "Chixia", "id": "2", "element": "Fusion", "weaponType": "Pistols"}, {"name": "Ciaccona", "id": "37", "element": "Aero", "weaponType": "Pistols"}, {"name": "Danjin", "id": "10", "element": "Havoc", "weaponType": "Sword"}, {"name": "Encore", "id": "8", "element": "Fusion", "weaponType": "Rectifier"}, {"name": "Galbrena", "id": "55", "element": "Fusion", "weaponType": "Pistols"}, {"name": "Iuno", "id": "48", "element": "Aero", "weaponType": "Gauntlets"}, {"name": "Jianxin", "id": "23", "element": "Aero", "weaponType": "Gauntlets"}, {"name": "Jinhsi", "id": "24", "element": "Spectro", "weaponType": "Broadblade"}, {"name": "Jiyan", "id": "11", "element": "Aero", "weaponType": "Broadblade"}, {"name": "Lingyang", "id": "14", "element": "Glacio", "weaponType": "Gauntlets"}, {"name": "Lumi", "id": "30", "element": "Electro", "weaponType": "Broadblade"}, {"name": "Lupa", "id": "46", "element": "Fusion", "weaponType": "Broadblade"}, {"name": "Luuk Herssen", "id": "54", "element": "Spectro", "weaponType": "Gauntlets"}, {"name": "Lynae", "id": "60", "element": "Spectro", "weaponType": "Pistols"}, {"name": "Mornye", "id": "61", "element": "Fusion", "weaponType": "Broadblade"}, {"name": "Mortefi", "id": "13", "element": "Fusion", "weaponType": "Pistols"}, {"name": "Phoebe", "id": "45", "element": "Spectro", "weaponType": "Rectifier"}, {"name": "Phrolova", "id": "41", "element": "Havoc", "weaponType": "Rectifier"}, {"name": "Qiuyuan", "id": "56", "element": "Aero", "weaponType": "Sword"}, {"name": "Roccia", "id": "33", "element": "Havoc", "weaponType": "Gauntlets"}, {"name": "Rover: Aero", "id": "5", "element": "Aero", "weaponType": "Sword"}, {"name": "Rover: Aero", "id": "4", "element": "Aero", "weaponType": "Sword"}, {"name": "Rover: Havoc", "id": "5", "element": "Havoc", "weaponType": "Sword"}, {"name": "Rover: Havoc", "id": "4", "element": "Havoc", "weaponType": "Sword"}, {"name": "Rover: Spectro", "id": "4", "element": "Spectro", "weaponType": "Sword"}, {"name": "Rover: Spectro", "id": "5", "element": "Spectro", "weaponType": "Sword"}, {"name": "Sanhua", "id": "7", "element": "Glacio", "weaponType": "Sword"}, {"name": "Shorekeeper", "id": "28", "element": "Spectro", "weaponType": "Rectifier"}, {"name": "Taoqi", "id": "9", "element": "Havoc", "weaponType": "Broadblade"}, {"name": "Verina", "id": "3", "element": "Spectro", "weaponType": "Rectifier"}, {"name": "Xiangli Yao", "id": "25", "element": "Electro", "weaponType": "Gauntlets"}, {"name": "Yangyang", "id": "1", "element": "Aero", "weaponType": "Sword"}, {"name": "Yinlin", "id": "17", "element": "Electro", "weaponType": "Rectifier"}, {"name": "Youhu", "id": "31", "element": "Glacio", "weaponType": "Gauntlets"}, {"name": "Yuanwu", "id": "15", "element": "Electro", "weaponType": "Gauntlets"}, {"name": "Zani", "id": "38", "element": "Spectro", "weaponType": "Gauntlets"}, {"name": "Zhezhi", "id": "27", "element": "Glacio", "weaponType": "Rectifier"}]